sparrow/.gitignore
sparrow/__init__.py
sparrow/__main__.py
sparrow/algorithm/.gitignore
sparrow/ann/__init__.py
sparrow/ann/hnsw.py
sparrow/ann/image_deduplication.py
sparrow/ann/image_utils.py
sparrow/ann/milvus_db/.gitignore
sparrow/ann/milvus_db/Makefile
sparrow/ann/milvus_db/docker-compose.yml
sparrow/ann/milvus_utils.py
sparrow/api/__init__.py
sparrow/api/common.py
sparrow/api/static/8dbd28457ff989b4568a.worker.js.LICENSE.txt
sparrow/api/static/8dbd28457ff989b4568a.worker.js.map
sparrow/api/static/favicon-16x16.png
sparrow/api/static/favicon-32x32.png
sparrow/api/static/icon-yuanian.png
sparrow/api/static/icon.png
sparrow/api/static/index.css
sparrow/api/static/index.html
sparrow/api/static/oauth2-redirect.html
sparrow/api/static/redoc.browser.lib.js
sparrow/api/static/redoc.browser.lib.js.LICENSE.txt
sparrow/api/static/redoc.browser.lib.js.map
sparrow/api/static/redoc.lib.js
sparrow/api/static/redoc.lib.js.LICENSE.txt
sparrow/api/static/redoc.lib.js.map
sparrow/api/static/redoc.standalone.js
sparrow/api/static/redoc.standalone.js.LICENSE.txt
sparrow/api/static/redoc.standalone.js.map
sparrow/api/static/swagger-initializer.js
sparrow/api/static/swagger-ui-bundle.js
sparrow/api/static/swagger-ui-bundle.js.map
sparrow/api/static/swagger-ui-es-bundle-core.js
sparrow/api/static/swagger-ui-es-bundle-core.js.map
sparrow/api/static/swagger-ui-es-bundle.js
sparrow/api/static/swagger-ui-es-bundle.js.map
sparrow/api/static/swagger-ui-standalone-preset.js
sparrow/api/static/swagger-ui-standalone-preset.js.map
sparrow/api/static/swagger-ui.css
sparrow/api/static/swagger-ui.css.map
sparrow/api/static/swagger-ui.js
sparrow/api/static/swagger-ui.js.map
sparrow/cli/__init__.py
sparrow/cli/core.py
sparrow/cli/demo.py
sparrow/cli/downloader.py
sparrow/cli/git.py
sparrow/cli/script.py
sparrow/cli/tree.py
sparrow/color/__init__.py
sparrow/color/color.py
sparrow/color/constant.py
sparrow/constant.py
sparrow/core.py
sparrow/cv/__init__.py
sparrow/cv/utils.py
sparrow_tool-0.8.7.dist-info/LICENSE
sparrow_tool-0.8.7.dist-info/METADATA
sparrow_tool-0.8.7.dist-info/WHEEL
sparrow_tool-0.8.7.dist-info/entry_points.txt
sparrow_tool-0.8.7.dist-info/RECORD
