Metadata-Version: 2.1
Name: sparrow-tool
Version: 0.8.7
Summary: 
Home-page: https://github.com/beidongjiedeguang/sparrow
Keywords: Machine Learning,nlp,cv,cli
Author: kunyuan
Author-email: beidongjiedeguang@gmail.com
Classifier: Development Status :: 5 - Production/Stable
Classifier: Operating System :: OS Independent
Classifier: Programming Language :: Python :: 2
Classifier: Programming Language :: Python :: 2.7
Classifier: Programming Language :: Python :: 3
Classifier: Programming Language :: Python :: 3.4
Classifier: Programming Language :: Python :: 3.5
Classifier: Programming Language :: Python :: 3.6
Classifier: Programming Language :: Python :: 3.7
Classifier: Programming Language :: Python :: 3.8
Classifier: Programming Language :: Python :: 3.9
Classifier: Programming Language :: Python :: 3.10
Classifier: Programming Language :: Python :: 3.11
Classifier: Programming Language :: Python :: 3
Classifier: Topic :: Software Development :: Build Tools
Classifier: Topic :: Software Development :: Libraries :: Python Modules
Requires-Dist: Deprecated
Requires-Dist: GitPython
Requires-Dist: attrs (>=22.1.0,<23.0.0)
Requires-Dist: chevron
Requires-Dist: colour
Requires-Dist: concurrent-log-handler
Requires-Dist: fire
Requires-Dist: gpustat (>=1.0.0,<2.0.0)
Requires-Dist: numpy
Requires-Dist: pandas (>=1.5.0,<2.0.0)
Requires-Dist: pendulum (>=2.1.2,<3.0.0)
Requires-Dist: pretty_errors (>=1.2.25,<2.0.0)
Requires-Dist: psutil (>=5.9.2,<6.0.0)
Requires-Dist: pyyaml
Requires-Dist: rich
Project-URL: Documentation, https://github.com/beidongjiedeguang/sparrow#sparrow_tool
Project-URL: Repository, https://github.com/beidongjiedeguang/sparrow
